{
  "flowName": "harmonize-flow",
  "Comment": "makes things",
  "contentDatabase": "state-conductor-content",
  "modulesDatabase": "state-conductor-modules",
  "context": [
    {
      "domain": "collection",
      "value": "flow-time"
    }
  ],
  "StartAt": "needs-envelope",
  "States": [
    {
      "stateName": "needs-envelope",
      "Type": "Task",
      "Comment": "makes the envelope",
      "Resource": "/state-conductor/actions/make-envelope.sjs",
      "Next": "needs-headers"
    },
    {
      "stateName": "needs-headers",
      "Type": "Task",
      "Comment": "makes the envelope's headers",
      "Resource": "/state-conductor/actions/make-headers.sjs",
      "Next": "needs-triples"
    },
    {
      "stateName": "needs-triples",
      "Type": "Task",
      "Comment": "makes the envelope's triples",
      "Resource": "/state-conductor/actions/make-triples.sjs",
      "Next": "success"
    }, 
    {
      "stateName": "success",
      "Type": "Succeed"
    }
  ]      
}